majortom_eg/MajorTom.py
majortom_eg/__about__.py
majortom_eg/__init__.py
majortom_eg-0.1.1.dist-info/METADATA
majortom_eg-0.1.1.dist-info/WHEEL
majortom_eg-0.1.1.dist-info/licenses/LICENSE.txt
majortom_eg-0.1.1.dist-info/RECORD
