Metadata-Version: 2.4
Name: majortom_eg
Version: 0.1.1
Summary: Implementation of the ESA MajorTom grid system
Project-URL: Documentation, https://github.com/earth-genome/majortom#readme
Project-URL: Issues, https://github.com/earth-genome/majortom/issues
Project-URL: Source, https://github.com/earth-genome/majortom
Author-email: tingold <hutch@earthgenome.org>
License-Expression: MIT
License-File: LICENSE.txt
Classifier: License :: OSI Approved :: MIT License
Classifier: Operating System :: OS Independent
Classifier: Programming Language :: Python :: 3
Requires-Python: >=3.8
Requires-Dist: geolib
Requires-Dist: numpy
Requires-Dist: shapely
